gakp_inet-0.2.9.dist-info/DESCRIPTION.rst
gakp_inet-0.2.9.dist-info/METADATA
gakp_inet-0.2.9.dist-info/RECORD
gakp_inet-0.2.9.dist-info/WHEEL
gakp_inet-0.2.9.dist-info/entry_points.txt
gakp_inet-0.2.9.dist-info/metadata.json
gakp_inet-0.2.9.dist-info/top_level.txt
inet/__init__.py
inet/client.py
inet/db.py
inet/errors.py
inet/inetserver.py
inet/message.py
inet/proxy.py
inet/router.py
inet/server.py
inet/sockets.py
