Metadata-Version: 2.0
Name: gakp-inet
Version: 0.2.9
Summary: UNKNOWN
Home-page: https://github.com/danceasarxx/inet
Author: Arewa Olakunle
Author-email: arewa.olakunle@gmail.com
License: BSD
Platform: any
Classifier: Development Status :: 4 - Beta
Classifier: Environment :: Console
Classifier: Intended Audience :: Developers
Classifier: License :: OSI Approved :: BSD License
Classifier: Operating System :: POSIX
Classifier: Operating System :: Unix
Classifier: Programming Language :: Python
Classifier: Programming Language :: Python :: 2
Classifier: Programming Language :: Python :: 3
Classifier: Topic :: Software Development :: Libraries :: Python Modules
Requires-Dist: gevent (==1.1.1)
Requires-Dist: gipc (==0.6.0)
Requires-Dist: greenlet (==0.4.9)
Requires-Dist: plac (==0.9.1)
Requires-Dist: pyzmq (==15.2.0)
Requires-Dist: zmq (==0.0.0)
